[
    {
        "content": "<p>Well, both the developer manual and the api docs works just fine. Generating the html is just about running antora and doxygen as part of the build.</p>\n<p>If we want to use dokuwiki in an open source context it must be possible to do something similar. It basically boils down to creating the html in cake code. </p>\n<p>If this not possible the best we could do is create a separate download similar to the current manual.</p>",
        "id": 451801502,
        "sender_full_name": "Alec Leamas",
        "timestamp": 1721146828
    },
    {
        "content": "<p>Cmake code, not cake</p>",
        "id": 451802091,
        "sender_full_name": "Alec Leamas",
        "timestamp": 1721146942
    }
]